population_synthesis_toolkit-1.1.3.dist-info/licenses/LICENSE
pst/SSP.py
pst/__init__.py
pst/_version.py
pst/dust.py
pst/models.py
pst/observables.py
pst/utils.py
pst/data/lick/lick_ha.json
pst/data/ssp/PopStar/popstar_cha_0.15_100.fits.gz
population_synthesis_toolkit-1.1.3.dist-info/METADATA
population_synthesis_toolkit-1.1.3.dist-info/WHEEL
population_synthesis_toolkit-1.1.3.dist-info/top_level.txt
population_synthesis_toolkit-1.1.3.dist-info/RECORD
