Metadata-Version: 2.4
Name: population-synthesis-toolkit
Version: 1.1.3
Summary: Population Synthesis Toolkit
Author-email: Yago Ascasibar <yago.ascasibar@uam.es>, Pablo Corcho-Caballero <p.corcho.caballero@rug.nl>, Daniel Jiménez-López <daniel.jimenezl@uam.es>
License: BSD 3-Clause License
Project-URL: Repository, https://github.com/paranoya/population-synthesis-toolkit
Project-URL: Issues, https://github.com/paranoya/population-synthesis-toolkit/issues
Keywords: astronomy,stellar population synthesis,SED fitting
Classifier: Development Status :: 3 - Alpha
Classifier: License :: Free for non-commercial use
Classifier: Intended Audience :: Education
Classifier: Intended Audience :: Science/Research
Classifier: Operating System :: POSIX :: Linux
Classifier: Operating System :: Microsoft :: Windows
Classifier: Operating System :: MacOS
Classifier: Programming Language :: Python :: 3
Classifier: Topic :: Scientific/Engineering :: Information Analysis
Classifier: Topic :: Scientific/Engineering :: Mathematics
Classifier: Topic :: Software Development :: Libraries :: Python Modules
Requires-Python: >=3.8
License-File: LICENSE
Requires-Dist: astropy>=5.0.0
Requires-Dist: numpy<2.0.0,>=1.20
Requires-Dist: matplotlib>=3.7.0
Requires-Dist: extinction>=0.4
Requires-Dist: scipy>=1.10
Requires-Dist: requests>=2.30
Dynamic: license-file
